Metadata-Version: 2.1
Name: securechat
Version: 0.0.0
Summary: SCH
Home-page: https://github.com/nawafalqari/sch
Author: Your Name
Author-email: your@email.com
Classifier: Development Status :: 1 - Planning
Classifier: Intended Audience :: Developers
Classifier: License :: OSI Approved :: MIT License
Classifier: Programming Language :: Python :: 3
Classifier: Programming Language :: Python :: 3.6
Classifier: Programming Language :: Python :: 3.7
Classifier: Programming Language :: Python :: 3.8
